{"BankNifty": {"16/02/2023": {"NRML": {"from": 41500.0, "to": 41700.0}, "MIS": "All Strikes Allowed"}, "23/02/2023": {"NRML": {"from": 41500.0, "to": 41700.0}, "MIS": {"from": 37500.0, "to": 45700.0}}, "02/03/2023": {"NRML": {"from": 41500.0, "to": 41700.0}, "MIS": {"from": 37500.0, "to": 45700.0}}}, "Nifty": {"16/02/2023": {"NRML": {"from": 17800.0, "to": 18300.0}, "MIS": "All Strikes Allowed"}, "23/02/2023": {"NRML": {"from": 17800.0, "to": 18300.0}, "MIS": {"from": 16250.0, "to": 19800.0}}, "02/03/2023": {"NRML": {"from": 17800.0, "to": 18300.0}, "MIS": {"from": 16250.0, "to": 19800.0}}}, "FinNifty": {"21/02/2023": {"NRML": {"from": 18500.0, "to": 18700.0}, "MIS": "All Strikes With Oi Over 500 Lots Allowed"}, "28/02/2023": {"NRML": {"from": 18500.0, "to": 18700.0}, "MIS": "All Strikes With Oi Over 500 Lots Allowed More Information"}}}