{"BankNifty": {"08/05/2024": {"NRML": {"from": 48500.0, "to": 49900.0}, "MIS": "All Strikes Allowed"}, "15/05/2024": {"NRML": {"from": 48900.0, "to": 49600.0}, "MIS": {"from": 44400.0, "to": 54100.0}}, "29/05/2024": {"NRML": {"from": 48900.0, "to": 49600.0}, "MIS": {"from": 44400.0, "to": 54100.0}}}, "Nifty": {"09/05/2024": {"NRML": {"from": 22350.0, "to": 22950.0}, "MIS": "All Strikes Allowed"}, "16/05/2024": {"NRML": {"from": 22350.0, "to": 22950.0}, "MIS": {"from": 20400.0, "to": 24900.0}}, "30/05/2024": {"NRML": {"from": 22350.0, "to": 22950.0}, "MIS": {"from": 20400.0, "to": 24900.0}}}, "FinNifty": {"07/05/2024": {"NRML": {"from": 21500.0, "to": 22300.0}, "MIS": "All Strikes With Oi Over 500 Lots Allowed"}, "28/05/2024": {"NRML": {"from": 19700.0, "to": 24000.0}, "MIS": "All Strikes With Oi Over 500 Lots Allowed More Information"}}}