{"BankNifty": {"31/07/2025": {"NRML": "All Strikes Allowed ", "MIS": "All Strikes Allowed"}, "28/08/2025": {"NRML": "All Strikes Allowed ", "MIS": "All Strikes Allowed"}, "30/09/2025": {"NRML": "All Strikes Allowed ", "MIS": "All Strikes Allowed"}}, "Nifty": {"03/07/2025": {"NRML": "All Strikes Allowed ", "MIS": "All Strikes Allowed"}, "10/07/2025": {"NRML": "All Strikes Allowed ", "MIS": "All Strikes Allowed"}, "17/07/2025": {"NRML": "All Strikes Allowed ", "MIS": "All Strikes Allowed"}}, "FinNifty": {"31/07/2025": {"NRML": "All Strikes Allowed  ", "MIS": "All Strikes With Oi Over 500 Lots Allowed"}}}