{"BankNifty": {"30/10/2024": {"NRML": {"from": 49800.0, "to": 52700.0}, "MIS": "All Strikes Allowed"}, "06/11/2024": {"NRML": {"from": 49800.0, "to": 52700.0}, "MIS": {"from": 46200.0, "to": 56300.0}}, "13/11/2024": {"NRML": {"from": 49800.0, "to": 52700.0}, "MIS": {"from": 46200.0, "to": 56300.0}}}, "Nifty": {"24/10/2024": {"NRML": "All Strikes Allowed ", "MIS": "All Strikes Allowed"}, "31/10/2024": {"NRML": {"from": 23950.0, "to": 24900.0}, "MIS": {"from": 22000.0, "to": 26850.0}}, "07/11/2024": {"NRML": {"from": 23950.0, "to": 24900.0}, "MIS": {"from": 22000.0, "to": 26850.0}}}, "FinNifty": {"29/10/2024": {"NRML": {"from": 23300.0, "to": 24200.0}, "MIS": "All Strikes With Oi Over 500 Lots Allowed"}, "05/11/2024": {"NRML": {"from": 23300.0, "to": 24200.0}, "MIS": "All Strikes With Oi Over 500 Lots Allowed More Information"}}}